mkdocs_advanced_seo/__init__.py
mkdocs_advanced_seo/plugin.py
mkdocs_advanced_seo-1.0.3.dist-info/METADATA
mkdocs_advanced_seo-1.0.3.dist-info/WHEEL
mkdocs_advanced_seo-1.0.3.dist-info/entry_points.txt
mkdocs_advanced_seo-1.0.3.dist-info/licenses/LICENSE
mkdocs_advanced_seo-1.0.3.dist-info/RECORD
