Metadata-Version: 2.4
Name: mkdocs-advanced-seo
Version: 1.0.3
Summary: A comprehensive SEO plugin for MkDocs with Advanced Meta tags, Open Graph, Twitter Cards, JSON-LD, and more.
Project-URL: Homepage, https://raineblog.dpdns.org/mkdocs-advanced-seo/
Project-URL: Documentation, https://raineblog.dpdns.org/mkdocs-advanced-seo/
Project-URL: Repository, https://github.com/raineblog/mkdocs-advanced-seo
Project-URL: Issues, https://github.com/raineblog/mkdocs-advanced-seo/issues
Author-email: RainPPR <2125773894@qq.com>
License-Expression: MIT
License-File: LICENSE
Keywords: json-ld,meta,mkdocs,open graph,plugin,seo
Classifier: Development Status :: 4 - Beta
Classifier: Intended Audience :: Developers
Classifier: License :: OSI Approved :: MIT License
Classifier: Operating System :: OS Independent
Classifier: Programming Language :: Python
Classifier: Programming Language :: Python :: 3
Classifier: Programming Language :: Python :: 3.8
Classifier: Programming Language :: Python :: 3.9
Classifier: Programming Language :: Python :: 3.10
Classifier: Programming Language :: Python :: 3.11
Classifier: Topic :: Documentation
Classifier: Topic :: Text Processing :: Markup :: Markdown
Requires-Python: >=3.8
Requires-Dist: beautifulsoup4>=4.11.0
Requires-Dist: mkdocs>=1.4.0
Requires-Dist: python-dateutil>=2.8.0
